ckanext/__init__.py
ckanext/ckanpackager/__init__.py
ckanext/ckanpackager/cli.py
ckanext/ckanpackager/plugin.py
ckanext/ckanpackager/model/__init__.py
ckanext/ckanpackager/model/stat.py
docs/_scripts/gen_api_pages.py
ckanext_ckanpackager-3.0.0.dist-info/LICENSE
ckanext_ckanpackager-3.0.0.dist-info/METADATA
ckanext_ckanpackager-3.0.0.dist-info/WHEEL
ckanext_ckanpackager-3.0.0.dist-info/entry_points.txt
ckanext_ckanpackager-3.0.0.dist-info/top_level.txt
ckanext_ckanpackager-3.0.0.dist-info/RECORD
