Metadata-Version: 2.1
Name: ckanext-ckanpackager
Version: 3.0.0
Summary: A CKAN extension that stores legacy download statistics from the deprecated service ckanpackager.
Author-email: Natural History Museum <data@nhm.ac.uk>
License: GPL-3.0-or-later
Project-URL: repository, https://github.com/NaturalHistoryMuseum/ckanext-ckanpackager
Project-URL: changelog, https://github.com/NaturalHistoryMuseum/ckanext-ckanpackager/blob/main/CHANGELOG.md
Keywords: CKAN,data,ckanpackager
Classifier: Development Status :: 5 - Production/Stable
Classifier: License :: OSI Approved :: GNU General Public License v3 (GPLv3)
Classifier: Programming Language :: Python
Classifier: Programming Language :: Python :: 3 :: Only
Classifier: Programming Language :: Python :: 3.6
Classifier: Programming Language :: Python :: 3.7
Classifier: Programming Language :: Python :: 3.8
Requires-Python: >=3.6
License-File: LICENSE
Requires-Dist: ckantools (>=0.3.0)
Provides-Extra: test
Requires-Dist: mock ; extra == 'test'
Requires-Dist: pytest (>=4.6.5) ; extra == 'test'
Requires-Dist: pytest-cov (>=2.7.1) ; extra == 'test'
Requires-Dist: coveralls ; extra == 'test'
